discordcss/__init__.py
discordcss/cli.py
discordcss-0.1.dist-info/METADATA
discordcss-0.1.dist-info/WHEEL
discordcss-0.1.dist-info/entry_points.txt
discordcss-0.1.dist-info/top_level.txt
discordcss-0.1.dist-info/RECORD
