Metadata-Version: 2.1
Name: discordcss
Version: 0.1
Requires-Dist: discord.py
